{"errors":[],"warnings":[],"namedChunkGroups":{"app":{"chunks":[4,1],"assets":["webpack-runtime-0d374797e7f312d97718.js","webpack-runtime-0d374797e7f312d97718.js.map","app-cd6a0700b50483c26741.js","app-cd6a0700b50483c26741.js.map"],"children":{},"childAssets":{}},"component---src-pages-about-mdx":{"chunks":[0,2],"assets":["0.d68d214a5799f6dc5826.css","0-6069a4a20a02f16f5e64.js","0-6069a4a20a02f16f5e64.js.map","component---src-pages-about-mdx.1da5a9b950fc28d8f4b2.css","component---src-pages-about-mdx-205d1b11d582ed4208f6.js","component---src-pages-about-mdx-205d1b11d582ed4208f6.js.map"],"children":{},"childAssets":{}},"component---src-pages-index-mdx":{"chunks":[0,3],"assets":["0.d68d214a5799f6dc5826.css","0-6069a4a20a02f16f5e64.js","0-6069a4a20a02f16f5e64.js.map","component---src-pages-index-mdx.1da5a9b950fc28d8f4b2.css","component---src-pages-index-mdx-032969ed7bfa3484a28c.js","component---src-pages-index-mdx-032969ed7bfa3484a28c.js.map"],"children":{},"childAssets":{}}},"assetsByChunkName":{"app":["webpack-runtime-0d374797e7f312d97718.js","app-cd6a0700b50483c26741.js"],"component---src-pages-about-mdx":["0.d68d214a5799f6dc5826.css","0-6069a4a20a02f16f5e64.js","component---src-pages-about-mdx.1da5a9b950fc28d8f4b2.css","component---src-pages-about-mdx-205d1b11d582ed4208f6.js"],"component---src-pages-index-mdx":["0.d68d214a5799f6dc5826.css","0-6069a4a20a02f16f5e64.js","component---src-pages-index-mdx.1da5a9b950fc28d8f4b2.css","component---src-pages-index-mdx-032969ed7bfa3484a28c.js"]}}